{
	"api/user/strInfo": {
		"success": true,
		"code": 200,
		"message": "成功",
		"data": {
			"info": [{
					"school": "河北软件技术学院",
					"class_id": "2",
					"str_attest_id": "1615273374546718722",
					"str_name": "张航",
					"str_number": 206307268,
					"avatar": "https://qj-school.oss-cn-beijing.aliyuncs.com/2023-01-06/308fc78b738e490299eff8441d042086avatar.png",
					"department": "软件工程系",
					"parentId": "1"
				},
				{
					"school": "河北软件技术学院",
					"class_id": "2",
					"str_attest_id": "1615273374546718723",
					"str_name": "李明",
					"str_number": 206307269,
					"avatar": "https://qj-school.oss-cn-beijing.aliyuncs.com/2023-01-06/308fc78b738e490299eff8441d042086avatar.png",
					"department": "软件工程系",
					"parentId": "1"
				},
				{
					"school": "河北软件技术学院",
					"class_id": "2",
					"str_attest_id": "1615273374546718724",
					"str_name": "王丽",
					"str_number": 206307270,
					"avatar": "https://qj-school.oss-cn-beijing.aliyuncs.com/2023-01-06/308fc78b738e490299eff8441d042086avatar.png",
					"department": "软件工程系",
					"parentId": "1"
				},
				{
					"school": "河北软件技术学院",
					"class_id": "2",
					"str_attest_id": "1615273374546718725",
					"str_name": "赵强",
					"str_number": 206307271,
					"avatar": "https://qj-school.oss-cn-beijing.aliyuncs.com/2023-01-06/308fc78b738e490299eff8441d042086avatar.png",
					"department": "软件工程系",
					"parentId": "1"
				},
				{
					"school": "河北软件技术学院",
					"class_id": "2",
					"str_attest_id": "1615273374546718726",
					"str_name": "陈红",
					"str_number": 206307272,
					"avatar": "https://qj-school.oss-cn-beijing.aliyuncs.com/2023-01-06/308fc78b738e490299eff8441d042086avatar.png",
					"department": "软件工程系",
					"parentId": "1"
				},
				{
					"school": "河北软件技术学院",
					"class_id": "2",
					"str_attest_id": "1615273374546718727",
					"str_name": "周军",
					"str_number": 206307273,
					"avatar": "https://qj-school.oss-cn-beijing.aliyuncs.com/2023-01-06/308fc78b738e490299eff8441d042086avatar.png",
					"department": "软件工程系",
					"parentId": "1"
				},
				{
					"school": "河北软件技术学院",
					"class_id": "2",
					"str_attest_id": "1615273374546718728",
					"str_name": "吴芳",
					"str_number": 206307274,
					"avatar": "https://qj-school.oss-cn-beijing.aliyuncs.com/2023-01-06/308fc78b738e490299eff8441d042086avatar.png",
					"department": "软件工程系",
					"parentId": "1"
				},
				{
					"school": "河北软件技术学院",
					"class_id": "2",
					"str_attest_id": "1615273374546718729",
					"str_name": "郑伟",
					"str_number": 206307275,
					"avatar": "https://qj-school.oss-cn-beijing.aliyuncs.com/2023-01-06/308fc78b738e490299eff8441d042086avatar.png",
					"department": "软件工程系",
					"parentId": "1"
				},
				{
					"school": "河北软件技术学院",
					"class_id": "2",
					"str_attest_id": "1615273374546718730",
					"str_name": "孙敏",
					"str_number": 206307276,
					"avatar": "https://qj-school.oss-cn-beijing.aliyuncs.com/2023-01-06/308fc78b738e490299eff8441d042086avatar.png",
					"department": "软件工程系",
					"parentId": "1"
				},
				{
					"school": "河北软件技术学院",
					"class_id": "2",
					"str_attest_id": "1615273374546718731",
					"str_name": "刘洋",
					"str_number": 206307277,
					"avatar": "https://qj-school.oss-cn-beijing.aliyuncs.com/2023-01-06/308fc78b738e490299eff8441d042086avatar.png",
					"department": "软件工程系",
					"parentId": "1"
				}
			]
		}
	},
	"api/fans/addFollow": [{
		"id": 1,
		"body": "Some comment",
		"postId": 1
	}],
	"api/account/login": {
		"name": "typicode"
	},
	"api/user/schoolInfo": {
		"name": "typicode"
	},
	"api/user/search": {
		"success": true,
		"code": 200,
		"message": "成功",
		"data": {
			"list": {
				"records": [{
						"userId": "1612743446986870786",
						"id": 100052,
						"userName": "用户100052",
						"classId": null,
						"phoneNumber": "",
						"signature": "这个用户摆烂，还没有个性签名",
						"fansNum": 0,
						"sex": "0",
						"avatar": "https://api.multiavatar.com/1612743446986870786.png",
						"fansState": false,
						"mutualConcern": false,
						"createTime": "1673342975754",
						"updateTime": "1673420290648",
						"sort": 0
					},
					{
						"userId": "1612743446986870787",
						"id": 100053,
						"userName": "用户100053",
						"classId": null,
						"phoneNumber": "",
						"signature": "这个用户正在寻找新朋友。",
						"fansNum": 12,
						"sex": "1",
						"avatar": "https://api.multiavatar.com/1612743446986870787.png",
						"fansState": true,
						"mutualConcern": true,
						"createTime": "1673342975755",
						"updateTime": "1673420290649",
						"sort": 1
					},
					{
						"userId": "1612743446986870788",
						"id": 100054,
						"userName": "用户100054",
						"classId": null,
						"phoneNumber": "",
						"signature": "喜欢旅行和美食。",
						"fansNum": 34,
						"sex": "2",
						"avatar": "https://api.multiavatar.com/1612743446986870788.png",
						"fansState": false,
						"mutualConcern": false,
						"createTime": "1673342975756",
						"updateTime": "1673420290650",
						"sort": 2
					},
					{
						"userId": "1612743446986870789",
						"id": 100055,
						"userName": "用户100055",
						"classId": null,
						"phoneNumber": "",
						"signature": "热爱生活，享受每一刻。",
						"fansNum": 67,
						"sex": "0",
						"avatar": "https://api.multiavatar.com/1612743446986870789.png",
						"fansState": true,
						"mutualConcern": true,
						"createTime": "1673342975757",
						"updateTime": "1673420290651",
						"sort": 3
					},
					{
						"userId": "1612743446986870790",
						"id": 100056,
						"userName": "用户100056",
						"classId": null,
						"phoneNumber": "",
						"signature": "探索未知，永不停息。",
						"fansNum": 100,
						"sex": "2",
						"avatar": "https://api.multiavatar.com/1612743446986870790.png",
						"fansState": false,
						"mutualConcern": false,
						"createTime": "1673342975758",
						"updateTime": "1673420290652",
						"sort": 4
					},
					{
						"userId": "1612743446986870791",
						"id": 100057,
						"userName": "用户100057",
						"classId": null,
						"phoneNumber": "",
						"signature": "人生就像一场马拉松。",
						"fansNum": 150,
						"sex": "1",
						"avatar": "https://api.multiavatar.com/1612743446986870791.png",
						"fansState": true,
						"mutualConcern": true,
						"createTime": "1673342975759",
						"updateTime": "1673420290653",
						"sort": 5
					},
					{
						"userId": "1612743446986870792",
						"id": 100058,
						"userName": "用户100058",
						"classId": null,
						"phoneNumber": "",
						"signature": "笑对人生，乐观向上。",
						"fansNum": 200,
						"sex": "0",
						"avatar": "https://api.multiavatar.com/1612743446986870792.png",
						"fansState": false,
						"mutualConcern": false,
						"createTime": "1673342975760",
						"updateTime": "1673420290654",
						"sort": 6
					},
					{
						"userId": "1612743446986870793",
						"id": 100059,
						"userName": "用户100059",
						"classId": null,
						"phoneNumber": "",
						"signature": "音乐与梦想同在。",
						"fansNum": 250,
						"sex": "2",
						"avatar": "https://api.multiavatar.com/1612743446986870793.png",
						"fansState": true,
						"mutualConcern": true,
						"createTime": "1673342975761",
						"updateTime": "1673420290655",
						"sort": 7
					},
					{
						"userId": "1612743446986870794",
						"id": 100060,
						"userName": "用户100060",
						"classId": null,
						"phoneNumber": "",
						"signature": "爱读书，爱思考。",
						"fansNum": 300,
						"sex": "1",
						"avatar": "https://api.multiavatar.com/1612743446986870794.png",
						"fansState": false,
						"mutualConcern": false,
						"createTime": "1673342975762",
						"updateTime": "1673420290656",
						"sort": 8
					},
					{
						"userId": "1612743446986870795",
						"id": 100061,
						"userName": "用户100061",
						"classId": null,
						"phoneNumber": "",
						"signature": "科技改变生活。",
						"fansNum": 350,
						"sex": "0",
						"avatar": "https://api.multiavatar.com/1612743446986870795.png",
						"fansState": true,
						"mutualConcern": true,
						"createTime": "1673342975763",
						"updateTime": "1673420290657",
						"sort": 9
					}
				],
				"total": 1,
				"size": 5,
				"current": 1,
				"orders": [],
				"optimizeCountSql": true,
				"searchCount": true,
				"countId": null,
				"maxLimit": null,
				"pages": 1
			}
		}
	},
	"api/user/department": {
		"name": "typicode"
	},
	"api/user/privateArticle": {
		"name": "typicode"
	},
	"api/user/personalInformation": {
		"name": "typicode"
	},
	"api/user/num": {
		"name": "typicode"
	},
	"api/user/modifyGoods": {
		"name": "typicode"
	},
	"api/IntactArticle/:articleId": {
		"name": "typicode"
	},
	"api/user/personalInformation": {
		"name": "typicode"
	},
	"api/user/userInfo": {
		"name": "typicode"
	},
	"api/ideafeedback/feedback": {
		"name": "typicode"
	},
	"api/user/auth": {
		"name": "typicode"
	},
	"api/fans/query": {
		"name": "typicode"
	},
	"api/account/userInfo": {
		"name": "typicode"
	},
	"api/account/auth": {
		"name": "typicode"
	},
	"api/account/reset-password": {
		"name": "typicode"
	},
	"api/account/register": {
		"name": "typicode"
	},
	"api/IntactArticle/allSearch": {
		"success": true,
		"code": 200,
		"message": "成功",
		"data": {
			"list": {
				"records": [{
						"article": {
							"title": "231",
							"content": "23",
							"createTime": "1673430635343",
							"commentNum": 18,
							"viewsNum": 257,
							"shareNum": 10,
							"likeNum": 0
						},
						"user": {
							"userName": "未设置用户名",
							"userId": "1610801362600222722",
							"avatar": "https://qj-school.oss-cn-beijing.aliyuncs.com/2023-01-06/308fc78b738e490299eff8441d042086avatar.png"
						},
						"image": {
							"articleImageId": "1613111118039969794",
							"imageLink": ""
						},
						"likeStatus": false,
						"fansState": false,
						"privateState": "0",
						"mutualConcern": false,
						"articleId": "1613111118048358401"
					},
					{
						"article": {
							"title": "11111111111",
							"content": "11111111111",
							"createTime": "1672994242127",
							"commentNum": 0,
							"viewsNum": 1,
							"shareNum": 0,
							"likeNum": 0
						},
						"user": {
							"userName": "未设置用户名",
							"userId": "1610801362600222722",
							"avatar": "https://qj-school.oss-cn-beijing.aliyuncs.com/2023-01-06/308fc78b738e490299eff8441d042086avatar.png"
						},
						"image": {
							"articleImageId": null,
							"imageLink": null
						},
						"likeStatus": false,
						"fansState": false,
						"privateState": "0",
						"mutualConcern": false,
						"articleId": "1611280752199114753"
					},
					{
						"article": {
							"title": "231",
							"content": "23",
							"createTime": "1672994094752",
							"commentNum": 0,
							"viewsNum": 1,
							"shareNum": 0,
							"likeNum": 0
						},
						"user": {
							"userName": "未设置用户名",
							"userId": "1610801362600222722",
							"avatar": "https://qj-school.oss-cn-beijing.aliyuncs.com/2023-01-06/308fc78b738e490299eff8441d042086avatar.png"
						},
						"image": {
							"articleImageId": null,
							"imageLink": null
						},
						"likeStatus": false,
						"fansState": false,
						"privateState": "0",
						"mutualConcern": false,
						"articleId": "1611280134063562753"
					},
					{
						"article": {
							"title": "123",
							"content": "123123",
							"createTime": "1672994059878",
							"commentNum": 0,
							"viewsNum": 1,
							"shareNum": 0,
							"likeNum": 0
						},
						"user": {
							"userName": "未设置用户名",
							"userId": "1610801362600222722",
							"avatar": "https://qj-school.oss-cn-beijing.aliyuncs.com/2023-01-06/308fc78b738e490299eff8441d042086avatar.png"
						},
						"image": {
							"articleImageId": null,
							"imageLink": null
						},
						"likeStatus": false,
						"fansState": false,
						"privateState": "0",
						"mutualConcern": false,
						"articleId": "1611279987791405058"
					},
					{
						"article": {
							"title": "123123",
							"content": "123123",
							"createTime": "1672994042756",
							"commentNum": 0,
							"viewsNum": 1,
							"shareNum": 0,
							"likeNum": 0
						},
						"user": {
							"userName": "未设置用户名",
							"userId": "1610801362600222722",
							"avatar": "https://qj-school.oss-cn-beijing.aliyuncs.com/2023-01-06/308fc78b738e490299eff8441d042086avatar.png"
						},
						"image": {
							"articleImageId": null,
							"imageLink": null
						},
						"likeStatus": false,
						"fansState": false,
						"privateState": "0",
						"mutualConcern": false,
						"articleId": "1611279915976531969"
					},
					{
						"article": {
							"title": "123",
							"content": "123",
							"createTime": "1672994002892",
							"commentNum": 0,
							"viewsNum": 2,
							"shareNum": 0,
							"likeNum": 0
						},
						"user": {
							"userName": "未设置用户名",
							"userId": "1610801362600222722",
							"avatar": "https://qj-school.oss-cn-beijing.aliyuncs.com/2023-01-06/308fc78b738e490299eff8441d042086avatar.png"
						},
						"image": {
							"articleImageId": null,
							"imageLink": null
						},
						"likeStatus": false,
						"fansState": false,
						"privateState": "0",
						"mutualConcern": false,
						"articleId": "1611279748762214403"
					},
					{
						"article": {
							"title": "123",
							"content": "123",
							"createTime": "1672993990121",
							"commentNum": 0,
							"viewsNum": 1,
							"shareNum": 0,
							"likeNum": 0
						},
						"user": {
							"userName": "未设置用户名",
							"userId": "1610801362600222722",
							"avatar": "https://qj-school.oss-cn-beijing.aliyuncs.com/2023-01-06/308fc78b738e490299eff8441d042086avatar.png"
						},
						"image": {
							"articleImageId": null,
							"imageLink": null
						},
						"likeStatus": false,
						"fansState": false,
						"privateState": "0",
						"mutualConcern": false,
						"articleId": "1611279695205146627"
					},
					{
						"article": {
							"title": "1231",
							"content": "23",
							"createTime": "1672993936041",
							"commentNum": 0,
							"viewsNum": 1,
							"shareNum": 0,
							"likeNum": 0
						},
						"user": {
							"userName": "未设置用户名",
							"userId": "1610801362600222722",
							"avatar": "https://qj-school.oss-cn-beijing.aliyuncs.com/2023-01-06/308fc78b738e490299eff8441d042086avatar.png"
						},
						"image": {
							"articleImageId": null,
							"imageLink": null
						},
						"likeStatus": false,
						"fansState": false,
						"privateState": "0",
						"mutualConcern": false,
						"articleId": "1611279468427517954"
					},
					{
						"article": {
							"title": "1231",
							"content": "123",
							"createTime": "1672993505369",
							"commentNum": 0,
							"viewsNum": 1,
							"shareNum": 0,
							"likeNum": 0
						},
						"user": {
							"userName": "未设置用户名",
							"userId": "1610801362600222722",
							"avatar": "https://qj-school.oss-cn-beijing.aliyuncs.com/2023-01-06/308fc78b738e490299eff8441d042086avatar.png"
						},
						"image": {
							"articleImageId": null,
							"imageLink": null
						},
						"likeStatus": false,
						"fansState": false,
						"privateState": "0",
						"mutualConcern": false,
						"articleId": "1611277662066610177"
					},
					{
						"article": {
							"title": "312312",
							"content": "1231231212",
							"createTime": "1672992241355",
							"commentNum": 0,
							"viewsNum": 1,
							"shareNum": 0,
							"likeNum": 0
						},
						"user": {
							"userName": "未设置用户名",
							"userId": "1610801362600222722",
							"avatar": "https://qj-school.oss-cn-beijing.aliyuncs.com/2023-01-06/308fc78b738e490299eff8441d042086avatar.png"
						},
						"image": {
							"articleImageId": null,
							"imageLink": null
						},
						"likeStatus": false,
						"fansState": false,
						"privateState": "0",
						"mutualConcern": false,
						"articleId": "1611272360353091585"
					}
				],
				"total": 47,
				"size": 10,
				"current": 1,
				"orders": [],
				"optimizeCountSql": true,
				"searchCount": true,
				"countId": null,
				"maxLimit": null,
				"pages": 5
			}
		}
	},
	"api/IntactArticle/:familyId": {
		"name": "typicode"
	},
	"api/IntactArticle/user-article": {
		"name": "typicode"
	},
	"api/user/activeUser": {
		"success": true,
		"code": 200,
		"message": "成功",
		"data": {
			"activeUser": [{
					"fansNum": 4,
					"sex": "0",
					"fansState": true,
					"avatar": "https://thirdwx.qlogo.cn/mmopen/vi_32/WQxaejTiaKZINeT2ibLhXl2kmGa3TvYiakmbCjPXRyXoH7Udl0GLoy7925MT2RIQh8gJf2Bgpo9oTz2YxQiaLm98icg/132",
					"userName": "True",
					"userId": "1570565996438142977",
					"mutualConcern": false
				},
				{
					"fansNum": 4,
					"sex": "0",
					"fansState": false,
					"avatar": "https://thirdwx.qlogo.cn/mmopen/vi_32/Q0j4TwGTfTKOHxVZKoHOYMJyfAp8Jqql16OdwDXLc9E3hf8NIVshwoKqbBcLftDVQia9oNgqKnPtelgXUzv9geQ/132",
					"userName": "chunshan",
					"userId": "1570573572345217025",
					"mutualConcern": false
				},
				{
					"fansNum": 5,
					"sex": "2",
					"fansState": false,
					"avatar": "https://qj-school.oss-cn-beijing.aliyuncs.com/2022-09-19/c0ee6f2762a64fabac7dc4542d4589fdtmp_4e040f7a4a04141ba18f50a2692c79287f076aecc9cfe997.jpg",
					"userName": "侯翠翠女士",
					"userId": "1571675256979030017",
					"mutualConcern": false
				},
				{
					"fansNum": 3,
					"sex": "0",
					"fansState": false,
					"avatar": "https://thirdwx.qlogo.cn/mmopen/vi_32/bDiblSkLbEgYqIbIlnfTINgyiaKgpXBjGGZ6Ed5DiaIUvj1vzFtI4H74mlEFtMhsFdp8CdJrTnMOibfpJwiaj8s0n0Q/132",
					"userName": "C°冷咖啡",
					"userId": "1571677958937083905",
					"mutualConcern": false
				},
				{
					"fansNum": 3,
					"sex": "0",
					"fansState": true,
					"avatar": "https://thirdwx.qlogo.cn/mmopen/vi_32/DYAIOgq83eoSaEu4zZM17Mf3N21iborBzvLwITPQJSIBPKMM0eaicnTBoJPhSiccqE33FtJrIKGlsWv5pb89fGZNg/132",
					"userName": "Aғᴛᴇʀᴡᴀʀᴅs .ᯤ⁵ᴳ",
					"userId": "1571678976747864065",
					"mutualConcern": false
				}
			]
		}
	},
	"api/article-like/:articleId": {
		"name": "typicode"
	},
	"api/article-classify/label-list": {
		"name": "typicode"
	},
	"api/IntactArticle/hottestRecommendation": {
		"name": "typicode"
	},
	"api/IntactArticle/contentPrompt": {
		"name": "typicode"
	},
	"api/share/addShare": {
		"name": "typicode"
	},
	"api/comment": {
		"name": "typicode"
	},
	"api/comment": {
		"name": "typicode"
	},
	"api/article-classify/topic-list": {
		"name": "typicode"
	},
	"api/IntactArticle/details/:articleId": {
		"name": "typicode"
	},
	"api/IntactArticle": {
		"name": "typicode"
	},
	"api/comment-like": {
		"name": "typicode"
	},
	"api/comment/:commentId": {
		"name": "typicode"
	},
	"api/chatMsg": {
		"name": "typicode"
	},
	"api/chatMsg/list": {
		"name": "typicode"
	},
	"api/chatMsg/send": {
		"name": "typicode"
	},
	"api/chatMsg/:acceptUserId": {
		"name": "typicode"
	},
	"api/user/search-goods": {
		"name": "typicode"
	},
	"api/user/modifyMyGoods": {
		"name": "typicode"
	},
	"api/carousel-figure/:figureId": {
		"name": "typicode"
	},
	"api/carousel_figure/:type": {
		"name": "typicode"
	},
	"api/carousel_figure": {
		"name": "typicode"
	},
	"api/IntactGoods/list": {
		"name": "typicode"
	},
	"api/IntactGoods": {
		"name": "typicode"
	},
	"api/IntactGoods/family": {
		"name": "typicode"
	},
	"api/IntactGoods": {
		"name": "typicode"
	},
	"api/common/upload-file": {
		"name": "typicode"
	},
	"api/account/validation-captcha/:type": {
		"name": "typicode"
	},
	"api/account/captcha": {
		"name": "typicode"
	},
	"api/common/delete-file": {
		"name": "typicode"
	},
	"api/account/captcha": {
		"name": "typicode"
	},
	"api/config/msg": {
		"name": "typicode"
	},
	"api/config/msg": {
		"name": "typicode"
	}
}